3robotics-0.0.1.dist-info/licenses/LICENSE
robodog/__init__.py
robodog/client.py
robodog/config.py
robodog/connection.py
robodog/controller.py
robodog/dog.py
robodog/states.py
robodog/subscriber.py
3robotics-0.0.1.dist-info/METADATA
3robotics-0.0.1.dist-info/WHEEL
3robotics-0.0.1.dist-info/entry_points.txt
3robotics-0.0.1.dist-info/top_level.txt
3robotics-0.0.1.dist-info/RECORD
