Metadata-Version: 2.4
Name: 3robotics
Version: 0.0.1
Summary: A Python library for controlling AlphaDog robotic dogs
Home-page: https://github.com/3robotics/3robotics
Author: 3robotics
Author-email: towardsrwby@gmail.com
Project-URL: Bug Tracker, https://github.com/3robotics/3robotics/issues
Project-URL: Documentation, https://github.com/3robotics/3robotics/wiki
Project-URL: Source Code, https://github.com/3robotics/3robotics
Keywords: robotics,alphadog,ros,robot control,python
Classifier: Development Status :: 4 - Beta
Classifier: Intended Audience :: Developers
Classifier: Topic :: Software Development :: Libraries :: Python Modules
Classifier: Topic :: Scientific/Engineering
Classifier: Programming Language :: Python :: 3
Classifier: Programming Language :: Python :: 3.9
Classifier: License :: OSI Approved :: MIT License
Classifier: Operating System :: OS Independent
Requires-Python: ==3.9.*
License-File: LICENSE
Requires-Dist: roslibpy>=1.3.0
Requires-Dist: dataclasses>=0.6; python_version < "3.7"
Requires-Dist: typing-extensions>=4.0.0
Provides-Extra: dev
Requires-Dist: pytest>=6.0; extra == "dev"
Requires-Dist: pytest-cov>=2.0; extra == "dev"
Requires-Dist: black>=22.0; extra == "dev"
Requires-Dist: isort>=5.0; extra == "dev"
Requires-Dist: flake8>=3.9; extra == "dev"
Provides-Extra: docs
Requires-Dist: sphinx>=4.0; extra == "docs"
Requires-Dist: sphinx-rtd-theme>=0.5; extra == "docs"
Dynamic: author
Dynamic: author-email
Dynamic: classifier
Dynamic: description
Dynamic: description-content-type
Dynamic: home-page
Dynamic: keywords
Dynamic: license-file
Dynamic: project-url
Dynamic: provides-extra
Dynamic: requires-dist
Dynamic: requires-python
Dynamic: summary
